src/__init__.py
src/api/gdpr_endpoints.py
src/api/quick_health_check.py
src/api/waitlist.py
src/auth/auth_helper.py
src/auth/auth_service.py
src/cli/__init__.py
src/cli/auth.py
src/cli/db.py
src/cli/main.py
src/cli/projects.py
src/cli/services.py
src/core/__init__.py
src/core/alert_explainer.py
src/core/alert_router.py
src/core/anomaly_detector.py
src/core/auto_runbook_executor.py
src/core/baseline_monitor.py
src/core/byok_tier.py
src/core/classifier.py
src/core/cost_tracker.py
src/core/dependency_analyzer.py
src/core/deployment_correlator.py
src/core/incident_memory.py
src/core/on_call_manager.py
src/core/postmortem_generator.py
src/core/rate_limiter.py
src/core/runbook_matcher.py
src/core/service_map_generator.py
src/core/team_assignment_system.py
src/integrations/email_notification_system.py
src/integrations/github_oauth.py
src/integrations/integrations_hub.py
src/integrations/pagerduty_integration.py
src/integrations/pagerduty_oauth.py
src/integrations/slack.py
src/integrations/slack_integration.py
src/integrations/slack_oauth.py
src/ml/__init__.py
src/ml/anomaly_detector.py
src/notifications/email_templates.py
src/setup/ai_setup.py
src/setup/supabase_setup.py
src/tools/chaos_engineering_tools.py
src/tools/custom_health_check_tool.py
src/tools/ssl_certificate_monitor.py
devops_sentinel-0.1.2.dist-info/METADATA
devops_sentinel-0.1.2.dist-info/WHEEL
devops_sentinel-0.1.2.dist-info/entry_points.txt
devops_sentinel-0.1.2.dist-info/top_level.txt
devops_sentinel-0.1.2.dist-info/RECORD
