Metadata-Version: 2.4
Name: devops-sentinel
Version: 0.1.2
Summary: Autonomous SRE agents that watch your services, detect anomalies, and generate blameless postmortems
Author-email: "jagadeep.mamidi" <jagadeep.mamidi@gmail.com>
License-Expression: MIT
Project-URL: Homepage, https://github.com/jagadeepmamidi/devops-sentinel
Project-URL: Documentation, https://devops-sentinel-i2ygm8zfs-jagadeeps-projects-10f14bee.vercel.app/
Project-URL: Repository, https://github.com/jagadeepmamidi/devops-sentinel
Project-URL: Issues, https://github.com/jagadeepmamidi/devops-sentinel/issues
Keywords: devops,sre,monitoring,incident-management,ai,postmortem
Classifier: Development Status :: 4 - Beta
Classifier: Environment :: Console
Classifier: Intended Audience :: Developers
Classifier: Intended Audience :: System Administrators
Classifier: Operating System :: OS Independent
Classifier: Programming Language :: Python :: 3
Classifier: Programming Language :: Python :: 3.10
Classifier: Programming Language :: Python :: 3.11
Classifier: Programming Language :: Python :: 3.12
Classifier: Topic :: System :: Monitoring
Classifier: Topic :: System :: Systems Administration
Requires-Python: >=3.10
Requires-Dist: click>=8.0
Requires-Dist: rich>=13.0
Requires-Dist: httpx>=0.25
Requires-Dist: aiohttp>=3.9
Requires-Dist: python-dotenv>=1.0
Requires-Dist: supabase>=2.0
Provides-Extra: dev
Requires-Dist: pytest>=7.0; extra == "dev"
Requires-Dist: pytest-asyncio>=0.21; extra == "dev"
Requires-Dist: pytest-cov>=4.0; extra == "dev"
Provides-Extra: ai
Requires-Dist: openai>=1.0; extra == "ai"
Requires-Dist: anthropic>=0.18; extra == "ai"
Provides-Extra: all
Requires-Dist: devops-sentinel[ai,dev]; extra == "all"
